ai_healthcheck/__init__.py
ai_healthcheck/models.py
ai_healthcheck/openai.py
ai_healthcheck-0.1.2.dist-info/METADATA
ai_healthcheck-0.1.2.dist-info/WHEEL
ai_healthcheck-0.1.2.dist-info/licenses/LICENSE
ai_healthcheck-0.1.2.dist-info/RECORD
