Metadata-Version: 2.4
Name: ai-healthcheck
Version: 0.1.2
Summary: Lightweight health checks for OpenAI
License: MIT
License-File: LICENSE
Keywords: openai,healthcheck,monitoring
Author: Minseok Song
Author-email: minseok.song@mssong.com
Requires-Python: >=3.10
Classifier: License :: OSI Approved :: MIT License
Classifier: Programming Language :: Python :: 3
Classifier: Programming Language :: Python :: 3.10
Classifier: Programming Language :: Python :: 3.11
Classifier: Programming Language :: Python :: 3.12
Classifier: Programming Language :: Python :: 3.13
Classifier: Programming Language :: Python :: 3.14
Requires-Dist: requests (>=2.28,<3)
Project-URL: Repository, https://github.com/skytin1004/ai-healthcheck
